[
  {
    "code": 200,
    "postId": "2082",
    "uniqueKeys": 5,
    "correctKeys": 5,
    "duplicateKeys": 0,
    "classifiedKeys": [
      {
        "identification": "\nMIICIjANBgkqhki",
        "orderedResults": [
          {
            "group": "II",
            "value": "0.3931135373"
          },
          {
            "group": "V",
            "value": "0.2337066030"
          },
          {
            "group": "VII",
            "value": "0.1971253225"
          },
          {
            "group": "VI",
            "value": "0.1715268942"
          },
          {
            "group": "III",
            "value": "0.0045276427"
          },
          {
            "group": "I",
            "value": null
          },
          {
            "group": "IV",
            "value": null
          }
        ],
        "rsaKey": {
          "modulusBitLen": 4096,
          "exponent": 65537
        },
        "mostAnonymous": false,
        "duplicated": false
      },
      {
        "identification": "\nMIICIjANBgkqhki",
        "orderedResults": [
          {
            "group": "VI",
            "value": "0.4940706141"
          },
          {
            "group": "V",
            "value": "0.2398310371"
          },
          {
            "group": "II",
            "value": "0.1524992895"
          },
          {
            "group": "VII",
            "value": "0.0734815703"
          },
          {
            "group": "III",
            "value": "0.0401174887"
          },
          {
            "group": "I",
            "value": null
          },
          {
            "group": "IV",
            "value": null
          }
        ],
        "rsaKey": {
          "modulusBitLen": 4096,
          "exponent": 65537
        },
        "mostAnonymous": false,
        "duplicated": false
      },
      {
        "identification": "\nMIICIjANBgkqhki",
        "orderedResults": [
          {
            "group": "II",
            "value": "0.4775610654"
          },
          {
            "group": "VII",
            "value": "0.2402797894"
          },
          {
            "group": "V",
            "value": "0.1779552692"
          },
          {
            "group": "VI",
            "value": "0.0955109609"
          },
          {
            "group": "III",
            "value": "0.0086929147"
          },
          {
            "group": "I",
            "value": null
          },
          {
            "group": "IV",
            "value": null
          }
        ],
        "rsaKey": {
          "modulusBitLen": 4096,
          "exponent": 65537
        },
        "mostAnonymous": false,
        "duplicated": false
      },
      {
        "identification": "\nMIICIjANBgkqhki",
        "orderedResults": [
          {
            "group": "IV",
            "value": "0.2966898630"
          },
          {
            "group": "I",
            "value": "0.2830787784"
          },
          {
            "group": "VI",
            "value": "0.1508850585"
          },
          {
            "group": "II",
            "value": "0.1067394102"
          },
          {
            "group": "V",
            "value": "0.1005703465"
          },
          {
            "group": "VII",
            "value": "0.0529556253"
          },
          {
            "group": "III",
            "value": "0.0090809179"
          }
        ],
        "rsaKey": {
          "modulusBitLen": 4096,
          "exponent": 65537
        },
        "mostAnonymous": true,
        "duplicated": false
      },
      {
        "identification": "\nMIICIjANBgkqhki",
        "orderedResults": [
          {
            "group": "II",
            "value": "0.3362751636"
          },
          {
            "group": "VI",
            "value": "0.2514527731"
          },
          {
            "group": "V",
            "value": "0.2355422953"
          },
          {
            "group": "VII",
            "value": "0.1675965652"
          },
          {
            "group": "III",
            "value": "0.0091332025"
          },
          {
            "group": "I",
            "value": null
          },
          {
            "group": "IV",
            "value": null
          }
        ],
        "rsaKey": {
          "modulusBitLen": 4096,
          "exponent": 65537
        },
        "mostAnonymous": false,
        "duplicated": false
      }
    ],
    "containerResults": [
      {
        "group": "II",
        "value": "0.6415066416"
      },
      {
        "group": "VI",
        "value": "0.1917096433"
      },
      {
        "group": "V",
        "value": "0.1475002992"
      },
      {
        "group": "VII",
        "value": "0.0192833342"
      },
      {
        "group": "III",
        "value": "0.0000000815"
      },
      {
        "group": "I",
        "value": null
      },
      {
        "group": "IV",
        "value": null
      }
    ],
    "maxNumberOfClassificationExceeded": false
  }
]
