[
  {
    "code": 200,
    "postId": "2110",
    "uniqueKeys": 5,
    "correctKeys": 5,
    "duplicateKeys": 0,
    "classifiedKeys": [
      {
        "identification": "\nMIICIjANBgkqhki",
        "orderedResults": [
          {
            "group": "II",
            "value": "0.4804024226"
          },
          {
            "group": "VII",
            "value": "0.2412233117"
          },
          {
            "group": "V",
            "value": "0.1777813607"
          },
          {
            "group": "VI",
            "value": "0.0968553771"
          },
          {
            "group": "III",
            "value": "0.0037375277"
          },
          {
            "group": "I",
            "value": null
          },
          {
            "group": "IV",
            "value": null
          }
        ],
        "rsaKey": {
          "modulusBitLen": 4096,
          "exponent": 65537
        },
        "mostAnonymous": false,
        "duplicated": false
      },
      {
        "identification": "\nMIICIjANBgkqhki",
        "orderedResults": [
          {
            "group": "IV",
            "value": "0.2663409492"
          },
          {
            "group": "I",
            "value": "0.2403251786"
          },
          {
            "group": "II",
            "value": "0.1579382121"
          },
          {
            "group": "VI",
            "value": "0.1344635677"
          },
          {
            "group": "V",
            "value": "0.1166691832"
          },
          {
            "group": "VII",
            "value": "0.0783130348"
          },
          {
            "group": "III",
            "value": "0.0059498739"
          }
        ],
        "rsaKey": {
          "modulusBitLen": 4096,
          "exponent": 65537
        },
        "mostAnonymous": true,
        "duplicated": false
      },
      {
        "identification": "\nMIICIjANBgkqhki",
        "orderedResults": [
          {
            "group": "II",
            "value": "0.4804024226"
          },
          {
            "group": "VII",
            "value": "0.2412233117"
          },
          {
            "group": "V",
            "value": "0.1777813607"
          },
          {
            "group": "VI",
            "value": "0.0968553771"
          },
          {
            "group": "III",
            "value": "0.0037375277"
          },
          {
            "group": "I",
            "value": null
          },
          {
            "group": "IV",
            "value": null
          }
        ],
        "rsaKey": {
          "modulusBitLen": 4096,
          "exponent": 65537
        },
        "mostAnonymous": false,
        "duplicated": false
      },
      {
        "identification": "\nMIICIjANBgkqhki",
        "orderedResults": [
          {
            "group": "II",
            "value": "0.4642188307"
          },
          {
            "group": "VII",
            "value": "0.2326576676"
          },
          {
            "group": "V",
            "value": "0.1724350604"
          },
          {
            "group": "VI",
            "value": "0.0921269524"
          },
          {
            "group": "III",
            "value": "0.0385614887"
          },
          {
            "group": "I",
            "value": null
          },
          {
            "group": "IV",
            "value": null
          }
        ],
        "rsaKey": {
          "modulusBitLen": 4096,
          "exponent": 65537
        },
        "mostAnonymous": false,
        "duplicated": false
      },
      {
        "identification": "\nMIICIjANBgkqhki",
        "orderedResults": [
          {
            "group": "II",
            "value": "0.4804024226"
          },
          {
            "group": "VII",
            "value": "0.2412233117"
          },
          {
            "group": "V",
            "value": "0.1777813607"
          },
          {
            "group": "VI",
            "value": "0.0968553771"
          },
          {
            "group": "III",
            "value": "0.0037375277"
          },
          {
            "group": "I",
            "value": null
          },
          {
            "group": "IV",
            "value": null
          }
        ],
        "rsaKey": {
          "modulusBitLen": 4096,
          "exponent": 65537
        },
        "mostAnonymous": false,
        "duplicated": false
      }
    ],
    "containerResults": [
      {
        "group": "II",
        "value": "0.9553353434"
      },
      {
        "group": "VII",
        "value": "0.0300565795"
      },
      {
        "group": "V",
        "value": "0.0132852798"
      },
      {
        "group": "VI",
        "value": "0.0013227958"
      },
      {
        "group": "III",
        "value": "0.0000000013"
      },
      {
        "group": "I",
        "value": null
      },
      {
        "group": "IV",
        "value": null
      }
    ],
    "maxNumberOfClassificationExceeded": false
  }
]
