[
  {
    "code": 200,
    "postId": "2267",
    "uniqueKeys": 5,
    "correctKeys": 5,
    "duplicateKeys": 0,
    "classifiedKeys": [
      {
        "identification": "\nMIICIjANBgkqhki",
        "orderedResults": [
          {
            "group": "II",
            "value": "0.3582768949"
          },
          {
            "group": "VII",
            "value": "0.1797950199"
          },
          {
            "group": "IV",
            "value": "0.1474675631"
          },
          {
            "group": "V",
            "value": "0.1323948958"
          },
          {
            "group": "I",
            "value": "0.0998400653"
          },
          {
            "group": "VI",
            "value": "0.0720214755"
          },
          {
            "group": "III",
            "value": "0.0102040852"
          }
        ],
        "rsaKey": {
          "modulusBitLen": 4096,
          "exponent": 65537
        },
        "mostAnonymous": false,
        "duplicated": false
      },
      {
        "identification": "\nMIICIjANBgkqhki",
        "orderedResults": [
          {
            "group": "II",
            "value": "0.4738078362"
          },
          {
            "group": "VII",
            "value": "0.2382444980"
          },
          {
            "group": "V",
            "value": "0.1766920751"
          },
          {
            "group": "VI",
            "value": "0.0941133647"
          },
          {
            "group": "III",
            "value": "0.0171422257"
          },
          {
            "group": "I",
            "value": null
          },
          {
            "group": "IV",
            "value": null
          }
        ],
        "rsaKey": {
          "modulusBitLen": 4096,
          "exponent": 65537
        },
        "mostAnonymous": false,
        "duplicated": false
      },
      {
        "identification": "\nMIICIjANBgkqhki",
        "orderedResults": [
          {
            "group": "II",
            "value": "0.3579270865"
          },
          {
            "group": "VII",
            "value": "0.1784133403"
          },
          {
            "group": "IV",
            "value": "0.1413853932"
          },
          {
            "group": "V",
            "value": "0.1314456969"
          },
          {
            "group": "I",
            "value": "0.0945063091"
          },
          {
            "group": "VI",
            "value": "0.0707160771"
          },
          {
            "group": "III",
            "value": "0.0256060965"
          }
        ],
        "rsaKey": {
          "modulusBitLen": 4096,
          "exponent": 65537
        },
        "mostAnonymous": true,
        "duplicated": false
      },
      {
        "identification": "\nMIICIjANBgkqhki",
        "orderedResults": [
          {
            "group": "II",
            "value": "0.3591575841"
          },
          {
            "group": "VII",
            "value": "0.1806718710"
          },
          {
            "group": "IV",
            "value": "0.1463306289"
          },
          {
            "group": "V",
            "value": "0.1327235886"
          },
          {
            "group": "I",
            "value": "0.1025172346"
          },
          {
            "group": "VI",
            "value": "0.0719953928"
          },
          {
            "group": "III",
            "value": "0.0066036997"
          }
        ],
        "rsaKey": {
          "modulusBitLen": 4096,
          "exponent": 65537
        },
        "mostAnonymous": false,
        "duplicated": false
      },
      {
        "identification": "\nMIICIjANBgkqhki",
        "orderedResults": [
          {
            "group": "II",
            "value": "0.3600379496"
          },
          {
            "group": "VII",
            "value": "0.1799935438"
          },
          {
            "group": "IV",
            "value": "0.1456962804"
          },
          {
            "group": "V",
            "value": "0.1318986970"
          },
          {
            "group": "I",
            "value": "0.1063670767"
          },
          {
            "group": "VI",
            "value": "0.0723717389"
          },
          {
            "group": "III",
            "value": "0.0036347132"
          }
        ],
        "rsaKey": {
          "modulusBitLen": 4096,
          "exponent": 65537
        },
        "mostAnonymous": false,
        "duplicated": false
      }
    ],
    "containerResults": [
      {
        "group": "II",
        "value": "0.9626481063"
      },
      {
        "group": "VII",
        "value": "0.0304504672"
      },
      {
        "group": "V",
        "value": "0.0065954118"
      },
      {
        "group": "VI",
        "value": "0.0003060014"
      },
      {
        "group": "III",
        "value": "0.0000000130"
      },
      {
        "group": "I",
        "value": null
      },
      {
        "group": "IV",
        "value": null
      }
    ],
    "maxNumberOfClassificationExceeded": false
  }
]
