[
  {
    "code": 200,
    "postId": "1456",
    "uniqueKeys": 5,
    "correctKeys": 5,
    "duplicateKeys": 0,
    "classifiedKeys": [
      {
        "identification": "\nMIICIjANBgkqhki",
        "orderedResults": [
          {
            "group": "II",
            "value": "0.3526048037"
          },
          {
            "group": "VII",
            "value": "0.1754422310"
          },
          {
            "group": "IV",
            "value": "0.1459168905"
          },
          {
            "group": "V",
            "value": "0.1298461236"
          },
          {
            "group": "I",
            "value": "0.0929800282"
          },
          {
            "group": "VI",
            "value": "0.0697898697"
          },
          {
            "group": "III",
            "value": "0.0334200530"
          }
        ],
        "rsaKey": {
          "modulusBitLen": 4096,
          "exponent": 65537
        },
        "mostAnonymous": true,
        "duplicated": false
      },
      {
        "identification": "\nMIICIjANBgkqhki",
        "orderedResults": [
          {
            "group": "II",
            "value": "0.3521743051"
          },
          {
            "group": "VII",
            "value": "0.1764907331"
          },
          {
            "group": "IV",
            "value": "0.1495304848"
          },
          {
            "group": "V",
            "value": "0.1348415565"
          },
          {
            "group": "I",
            "value": "0.1108836208"
          },
          {
            "group": "VI",
            "value": "0.0734640540"
          },
          {
            "group": "III",
            "value": "0.0026152452"
          }
        ],
        "rsaKey": {
          "modulusBitLen": 4096,
          "exponent": 65537
        },
        "mostAnonymous": false,
        "duplicated": false
      },
      {
        "identification": "\nMIICIjANBgkqhki",
        "orderedResults": [
          {
            "group": "II",
            "value": "0.4752177530"
          },
          {
            "group": "VII",
            "value": "0.2381575134"
          },
          {
            "group": "V",
            "value": "0.1763007076"
          },
          {
            "group": "VI",
            "value": "0.0942097678"
          },
          {
            "group": "III",
            "value": "0.0161142580"
          },
          {
            "group": "I",
            "value": null
          },
          {
            "group": "IV",
            "value": null
          }
        ],
        "rsaKey": {
          "modulusBitLen": 4096,
          "exponent": 65537
        },
        "mostAnonymous": false,
        "duplicated": false
      },
      {
        "identification": "\nMIICIjANBgkqhki",
        "orderedResults": [
          {
            "group": "II",
            "value": "0.3734049175"
          },
          {
            "group": "V",
            "value": "0.2343186517"
          },
          {
            "group": "VI",
            "value": "0.1996204665"
          },
          {
            "group": "VII",
            "value": "0.1871771910"
          },
          {
            "group": "III",
            "value": "0.0054787730"
          },
          {
            "group": "I",
            "value": null
          },
          {
            "group": "IV",
            "value": null
          }
        ],
        "rsaKey": {
          "modulusBitLen": 4096,
          "exponent": 65537
        },
        "mostAnonymous": false,
        "duplicated": false
      },
      {
        "identification": "\nMIICIjANBgkqhki",
        "orderedResults": [
          {
            "group": "II",
            "value": "0.4328984751"
          },
          {
            "group": "V",
            "value": "0.2241112722"
          },
          {
            "group": "VII",
            "value": "0.2170220926"
          },
          {
            "group": "VI",
            "value": "0.1228471779"
          },
          {
            "group": "III",
            "value": "0.0031209819"
          },
          {
            "group": "I",
            "value": null
          },
          {
            "group": "IV",
            "value": null
          }
        ],
        "rsaKey": {
          "modulusBitLen": 4096,
          "exponent": 65537
        },
        "mostAnonymous": false,
        "duplicated": false
      }
    ],
    "containerResults": [
      {
        "group": "II",
        "value": "0.9527094610"
      },
      {
        "group": "VII",
        "value": "0.0299180333"
      },
      {
        "group": "V",
        "value": "0.0161894911"
      },
      {
        "group": "VI",
        "value": "0.0011830122"
      },
      {
        "group": "III",
        "value": "0.0000000021"
      },
      {
        "group": "I",
        "value": null
      },
      {
        "group": "IV",
        "value": null
      }
    ],
    "maxNumberOfClassificationExceeded": false
  }
]
