[
  {
    "code": 200,
    "postId": "1961",
    "uniqueKeys": 5,
    "correctKeys": 5,
    "duplicateKeys": 0,
    "classifiedKeys": [
      {
        "identification": "\nMIICIjANBgkqhki",
        "orderedResults": [
          {
            "group": "II",
            "value": "0.4724482468"
          },
          {
            "group": "VII",
            "value": "0.2365254970"
          },
          {
            "group": "V",
            "value": "0.1734754987"
          },
          {
            "group": "VI",
            "value": "0.0940358091"
          },
          {
            "group": "III",
            "value": "0.0235149482"
          },
          {
            "group": "I",
            "value": null
          },
          {
            "group": "IV",
            "value": null
          }
        ],
        "rsaKey": {
          "modulusBitLen": 4096,
          "exponent": 65537
        },
        "mostAnonymous": false,
        "duplicated": false
      },
      {
        "identification": "\nMIICIjANBgkqhki",
        "orderedResults": [
          {
            "group": "II",
            "value": "0.3595614880"
          },
          {
            "group": "VII",
            "value": "0.1804794240"
          },
          {
            "group": "IV",
            "value": "0.1457150268"
          },
          {
            "group": "V",
            "value": "0.1329113976"
          },
          {
            "group": "I",
            "value": "0.1044881445"
          },
          {
            "group": "VI",
            "value": "0.0718101838"
          },
          {
            "group": "III",
            "value": "0.0050343350"
          }
        ],
        "rsaKey": {
          "modulusBitLen": 4096,
          "exponent": 65537
        },
        "mostAnonymous": false,
        "duplicated": false
      },
      {
        "identification": "\nMIICIjANBgkqhki",
        "orderedResults": [
          {
            "group": "VI",
            "value": "0.3970109015"
          },
          {
            "group": "V",
            "value": "0.2386521812"
          },
          {
            "group": "II",
            "value": "0.2271575585"
          },
          {
            "group": "VII",
            "value": "0.1116145164"
          },
          {
            "group": "III",
            "value": "0.0255648421"
          },
          {
            "group": "I",
            "value": "0.0000000000"
          },
          {
            "group": "IV",
            "value": null
          }
        ],
        "rsaKey": {
          "modulusBitLen": 4096,
          "exponent": 65537
        },
        "mostAnonymous": false,
        "duplicated": false
      },
      {
        "identification": "\nMIICIjANBgkqhki",
        "orderedResults": [
          {
            "group": "IV",
            "value": "0.2966898630"
          },
          {
            "group": "I",
            "value": "0.2830787784"
          },
          {
            "group": "VI",
            "value": "0.1508850585"
          },
          {
            "group": "II",
            "value": "0.1067394102"
          },
          {
            "group": "V",
            "value": "0.1005703465"
          },
          {
            "group": "VII",
            "value": "0.0529556253"
          },
          {
            "group": "III",
            "value": "0.0090809179"
          }
        ],
        "rsaKey": {
          "modulusBitLen": 4096,
          "exponent": 65537
        },
        "mostAnonymous": true,
        "duplicated": false
      },
      {
        "identification": "\nMIICIjANBgkqhki",
        "orderedResults": [
          {
            "group": "II",
            "value": "0.3597051304"
          },
          {
            "group": "VII",
            "value": "0.1806221483"
          },
          {
            "group": "IV",
            "value": "0.1461043234"
          },
          {
            "group": "V",
            "value": "0.1329582825"
          },
          {
            "group": "I",
            "value": "0.1050552426"
          },
          {
            "group": "VI",
            "value": "0.0724121196"
          },
          {
            "group": "III",
            "value": "0.0031427528"
          }
        ],
        "rsaKey": {
          "modulusBitLen": 4096,
          "exponent": 65537
        },
        "mostAnonymous": false,
        "duplicated": false
      }
    ],
    "containerResults": [
      {
        "group": "II",
        "value": "0.9089320543"
      },
      {
        "group": "V",
        "value": "0.0451394745"
      },
      {
        "group": "VII",
        "value": "0.0279585617"
      },
      {
        "group": "VI",
        "value": "0.0179698563"
      },
      {
        "group": "III",
        "value": "0.0000000529"
      },
      {
        "group": "I",
        "value": null
      },
      {
        "group": "IV",
        "value": null
      }
    ],
    "maxNumberOfClassificationExceeded": false
  }
]
